{
  "openapi": "3.0.1",
  "info": {
    "title": "EmployeeService",
    "version": "1.0"
  },
  "paths": {
    "/api/Employee": {
      "get": {
        "tags": [
          "Employee"
        ],
        "parameters": [
          {
            "name": "City",
            "in": "query",
            "schema": {
              "type": "string"
            }
          },
          {
            "name": "Age",
            "in": "query",
            "schema": {
              "type": "integer",
              "format": "int32"
            }
          },
          {
            "name": "SortBy",
            "in": "query",
            "schema": {
              "type": "string"
            }
          },
          {
            "name": "SortOrder",
            "in": "query",
            "schema": {
              "type": "string"
            }
          }
        ],
        "responses": {
          "200": {
            "description": "OK"
          }
        }
      },
      "post": {
        "tags": [
          "Employee"
        ],
        "requestBody": {
          "content": {
            "application/json": {
              "schema": {
                "$ref": "#/components/schemas/Employee"
              }
            },
            "text/json": {
              "schema": {
                "$ref": "#/components/schemas/Employee"
              }
            },
            "application/*+json": {
              "schema": {
                "$ref": "#/components/schemas/Employee"
              }
            }
          }
        },
        "responses": {
          "200": {
            "description": "OK"
          }
        }
      }
    }
  },
  "components": {
    "schemas": {
      "Employee": {
        "type": "object",
        "properties": {
          "id": {
            "type": "integer",
            "format": "int32"
          },
          "name": {
            "type": "string",
            "nullable": true
          },
          "age": {
            "type": "integer",
            "format": "int32"
          },
          "city": {
            "type": "string",
            "nullable": true
          }
        },
        "additionalProperties": false
      }
    }
  }
}